pygal/__about__.py
pygal/__init__.py
pygal/_compat.py
pygal/adapters.py
pygal/colors.py
pygal/config.py
pygal/etree.py
pygal/formatters.py
pygal/interpolate.py
pygal/serie.py
pygal/state.py
pygal/stats.py
pygal/style.py
pygal/svg.py
pygal/table.py
pygal/util.py
pygal/view.py
pygal/css/base.css
pygal/css/graph.css
pygal/css/style.css
pygal/graph/__init__.py
pygal/graph/bar.py
pygal/graph/base.py
pygal/graph/box.py
pygal/graph/dot.py
pygal/graph/dual.py
pygal/graph/funnel.py
pygal/graph/gauge.py
pygal/graph/graph.py
pygal/graph/histogram.py
pygal/graph/horizontal.py
pygal/graph/horizontalbar.py
pygal/graph/horizontalline.py
pygal/graph/horizontalstackedbar.py
pygal/graph/horizontalstackedline.py
pygal/graph/line.py
pygal/graph/map.py
pygal/graph/pie.py
pygal/graph/public.py
pygal/graph/pyramid.py
pygal/graph/radar.py
pygal/graph/solidgauge.py
pygal/graph/stackedbar.py
pygal/graph/stackedline.py
pygal/graph/time.py
pygal/graph/treemap.py
pygal/graph/xy.py
pygal/maps/__init__.py
pygal/test/__init__.py
pygal/test/conftest.py
pygal/test/test_bar.py
pygal/test/test_box.py
pygal/test/test_colors.py
pygal/test/test_config.py
pygal/test/test_date.py
pygal/test/test_formatters.py
pygal/test/test_gauge.py
pygal/test/test_graph.py
pygal/test/test_histogram.py
pygal/test/test_interpolate.py
pygal/test/test_line.py
pygal/test/test_line_log_none_max_solved.py
pygal/test/test_maps.py
pygal/test/test_pie.py
pygal/test/test_serie_config.py
pygal/test/test_sparktext.py
pygal/test/test_stacked.py
pygal/test/test_style.py
pygal/test/test_table.py
pygal/test/test_util.py
pygal/test/test_view.py
pygal/test/test_xml_filters.py
pygal/test/utils.py
pygal-3.1.0.data/scripts/pygal_gen.py
pygal-3.1.0.dist-info/COPYING
pygal-3.1.0.dist-info/METADATA
pygal-3.1.0.dist-info/WHEEL
pygal-3.1.0.dist-info/top_level.txt
pygal-3.1.0.dist-info/RECORD
