Metadata-Version: 2.1
Name: pygal
Version: 3.1.0
Summary: A Python svg graph plotting library
Home-page: https://www.pygal.org/
Author: Kozea
Author-email: dev@kozea.fr
License: GNU LGPL v3+
Keywords: svg,chart,graph,diagram,plot,histogram,kiviat
Platform: Any
Classifier: Development Status :: 4 - Beta
Classifier: Environment :: Console
Classifier: Intended Audience :: End Users/Desktop
Classifier: License :: OSI Approved :: GNU Lesser General Public License v3 or later (LGPLv3+)
Classifier: Operating System :: OS Independent
Classifier: Programming Language :: Python :: 3
Classifier: Topic :: Multimedia :: Graphics :: Presentation
Provides: pygal
Requires-Python: >=3.8
License-File: COPYING
Requires-Dist: importlib-metadata
Provides-Extra: lxml
Requires-Dist: lxml; extra == "lxml"
Provides-Extra: docs
Requires-Dist: sphinx; extra == "docs"
Requires-Dist: sphinx_rtd_theme; extra == "docs"
Requires-Dist: pygal_sphinx_directives; extra == "docs"
Provides-Extra: png
Requires-Dist: cairosvg; extra == "png"
Provides-Extra: test
Requires-Dist: cairosvg; extra == "test"
Requires-Dist: coveralls; extra == "test"
Requires-Dist: lxml; extra == "test"
Requires-Dist: pyquery; extra == "test"
Requires-Dist: pytest; extra == "test"
Requires-Dist: pytest-cov; extra == "test"
Requires-Dist: ruff>=0.5.6; extra == "test"
Provides-Extra: moulinrouge
Requires-Dist: flask; extra == "moulinrouge"
Requires-Dist: pygal_maps_ch; extra == "moulinrouge"
Requires-Dist: pygal_maps_fr; extra == "moulinrouge"
Requires-Dist: pygal_maps_world; extra == "moulinrouge"
